mistune_json/__init__.py
mistune_json/json_renderer.py
mistune_json-0.1.0.dist-info/METADATA
mistune_json-0.1.0.dist-info/WHEEL
mistune_json-0.1.0.dist-info/RECORD
