Metadata-Version: 2.3
Name: mistune-json
Version: 0.1.0
Summary: 
License: MIT
Author: fernandonino
Author-email: nino.fernando@gmail.com
Requires-Python: >=3.12
Classifier: License :: OSI Approved :: MIT License
Classifier: Programming Language :: Python :: 3
Classifier: Programming Language :: Python :: 3.12
Classifier: Programming Language :: Python :: 3.13
Requires-Dist: mistune (>=3.1.3,<4.0.0)
